othertools
