Metadata-Version: 2.1
Name: othertools
Version: 1.0.12
Summary: Other Tools
Home-page: https://github.com/zeuscronos/python-other-tools
Author: Zeus Cronos
Author-email: noreply@notavailable.com
License: Apache 2.0
Platform: UNKNOWN
